{
  "appPageId" : "c08e8a4e-d914-4404-81b7-8f4345965252",
  "componentName" : "siteforce:sldsOneColLayout",
  "dataProviders" : [ ],
  "id" : "ea5ade23-8946-4e46-ba08-1105f70fdb53",
  "label" : "Record List",
  "regions" : [ {
    "id" : "f599d5ad-a3bc-430c-add7-23b9b19de433",
    "regionName" : "header",
    "type" : "region"
  }, {
    "components" : [ {
      "componentAttributes" : {
        "enableInlineEdit" : true,
        "filterName" : "{!filterId}",
        "layout" : "FULL",
        "pageSize" : 25,
        "scope" : "{!objectName}",
        "showActionBar" : true,
        "showChartsPanel" : true,
        "showDisplay" : "showall",
        "showFilterPanel" : true,
        "showImageIcon" : true,
        "showManualRefreshButton" : true,
        "showObjectName" : true,
        "showPinnedList" : true,
        "showSearchBar" : true
      },
      "componentName" : "forceCommunity:objectHome",
      "id" : "9c141a3d-160e-419d-874e-0fc90b871f93",
      "renderPriority" : "NEUTRAL",
      "renditionMap" : { },
      "type" : "component"
    } ],
    "id" : "9fba10d3-8398-429d-9494-a03356842c22",
    "regionName" : "content",
    "type" : "region"
  }, {
    "id" : "82e68264-ffdb-4fbd-b7f7-a64565d0c5b3",
    "regionName" : "footer",
    "type" : "region"
  } ],
  "themeLayoutType" : "Inner",
  "type" : "view",
  "viewType" : "list"
}